[

 {
    "appIcon": "https://www.dropbox.com/s/myw0upk4va2f2w3/popcorn_time.png?dl=1",
    "appName": "Popcorn Time",
    "appDescription": "تطبيق مشاهدة و تحميل الافلام و المسلسلات العالمية مجانا",
    "url": "https://appgallery.cloud.huawei.com/marketshare/app/C102587339?locale=en_GB&source=appshare&subsource=C102587339"
  },
  
  {
    "appIcon": "https://www.dropbox.com/s/qjaiutyve34rkt5/newIcon.png?dl=1",
    "appName": "تطبيق تحميل و تحديث الواتساب",
    "appDescription": "تحميل و تحديث الواتساب",
    "url": "https://appgallery.cloud.huawei.com/marketshare/app/C101529045?locale=en_GB&source=appshare&subsource=C101529045"
  },

  {
    "appIcon": "https://www.dropbox.com/s/9f0aennilriugm9/icon.png?dl=1",
    "appName": "تطبيق تنصيب لعبة بابجي",
    "appDescription": "تمتع بلعبة PUBG",
    "url": "https://appgallery.cloud.huawei.com/marketshare/app/C101757193?locale=en_GB&source=appshare&subsource=C101757193"
  },

  {
    "appIcon": "https://www.dropbox.com/s/8zwgj4l70vtft4i/collage_app.png?dl=1",
    "appName": "تطبيق التعديل على الصور",
    "appDescription": "فلترات و مؤثرات مميزة",
    "url": "https://appgallery.cloud.huawei.com/marketshare/app/C101607759?locale=en_GB&source=appshare&subsource=C101607759"
  },

  {
    "appIcon": "https://www.dropbox.com/s/r4q9lgj44xcmheu/call-recorder-pro.png?dl=1",
    "appName": "تطبيق تسجيل المكالمات",
    "appDescription": "تسجيل المكالمات الواردة و الصادرة أوتوماتيكيا",
    "url": "https://appgallery.cloud.huawei.com/marketshare/app/C102250619?locale=en_GB&source=appshare&subsource=C102250619"
  },
  
    {
    "appIcon": "https://www.dropbox.com/s/e4n8um7k3rzgx23/flash-compass.png?dl=1",
    "appName": "تطبيق فلاش و بوصلة",
    "appDescription": "تطبيق عملي و ضروري لكل مستعمل هاتف",
    "url": "https://appgallery.cloud.huawei.com/marketshare/app/C102317871?locale=en_GB&source=appshare&subsource=102317871"
  },
  
  {
    "appIcon": "https://images2.imgbox.com/d6/8e/g04pVXBj_o.png",
    "appName": "تحميل الفيديو من الفايسبوك",
    "appDescription": "أفضل تطبيق مجاني للتحميل من الفايسبوك",
    "url": "https://appgallery.cloud.huawei.com/marketshare/app/C101544659"
  },
  {
    "appIcon": "https://www.dropbox.com/s/8daegf80bysfqfu/duplicate_file_remover.png?dl=1",
    "appName": "تطبيق حذف الملفات المكررة",
    "appDescription": "تنظيف فعال لإزالة الملفات المكررة من هاتفك",
    "url": "https://appgallery.cloud.huawei.com/marketshare/app/C102188107?locale=en_GB&source=appshare&subsource=C102188107"
  },

  {
    "appIcon": "https://www.dropbox.com/s/918go7wh6d6tup2/stickers.png?dl=1",
    "appName": "ستيكرز للواتساب",
    "appDescription": "إجعل رسائل الواتساب أكثر تميزا مع هذا التطبيق المجاني",
    "url": "https://appgallery.cloud.huawei.com/marketshare/app/C101552773?locale=en_GB&source=appshare&subsource=C101552773"
  }

]
